d7/__init__.py
d7/dice_expression.py
d7-1.0.1.dist-info/LICENSE
d7-1.0.1.dist-info/METADATA
d7-1.0.1.dist-info/WHEEL
d7-1.0.1.dist-info/top_level.txt
d7-1.0.1.dist-info/RECORD
