Metadata-Version: 2.1
Name: d7
Version: 1.0.1
Summary: A comprehensive Python-based dice notation interpreter and roller
Home-page: https://github.com/NunoCastanho/d7
Author: Nuno Castanho
Author-email: nuno.castanho.98@gmail.com
Project-URL: Bug Tracker, https://github.com/NunoCastanho/d7/issues
Classifier: Programming Language :: Python :: 3
Classifier: License :: OSI Approved :: MIT License
Classifier: Operating System :: OS Independent
Requires-Python: >=3.6
License-File: LICENSE
